hinen_open_api/__init__.py
hinen_open_api/client.py
hinen_open_api/exceptions.py
hinen_open_api/models.py
hinen_open_api/utils.py
hinen_open_api-1.0.1.dist-info/licenses/LICENSE
hinen_open_api-1.0.1.dist-info/METADATA
hinen_open_api-1.0.1.dist-info/WHEEL
hinen_open_api-1.0.1.dist-info/top_level.txt
hinen_open_api-1.0.1.dist-info/RECORD
