Metadata-Version: 2.4
Name: hinen-open-api
Version: 1.0.1
Summary: Hinen Open API Client
Author: Hinen-WeiFeng
License: MIT
Project-URL: Homepage, https://github.com/Hinen-IoT/hinen_open_api.git
Classifier: Development Status :: 3 - Alpha
Classifier: Intended Audience :: Developers
Classifier: License :: OSI Approved :: MIT License
Classifier: Operating System :: OS Independent
Classifier: Programming Language :: Python :: 3
Classifier: Programming Language :: Python :: 3.9
Classifier: Programming Language :: Python :: 3.10
Classifier: Programming Language :: Python :: 3.11
Requires-Python: >=3.9
License-File: LICENSE
Requires-Dist: aiohttp<4.0.0,>=3.8.0
Requires-Dist: pydantic<3.0.0,>=2.0.0
Requires-Dist: yarl<2.0.0,>=1.9.0
Provides-Extra: dev
Requires-Dist: pytest>=6.0; extra == "dev"
Requires-Dist: pytest-asyncio>=0.15; extra == "dev"
Requires-Dist: black>=21.0; extra == "dev"
Requires-Dist: flake8>=3.9; extra == "dev"
Dynamic: license-file
